<?xml version = '1.0' encoding = 'UTF-8'?>
<Diagram class="oracle.dbtools.crest.swingui.logical.DPVLogical" name="Logical" id="4F840449-6918-4D4A-DE17-964B3DE12119">
<createdBy>Jakub</createdBy>
<modifiedBy>Jakub</modifiedBy>
<createdTime>2017-10-07 13:51:48 UTC</createdTime>
<autoRoute>false</autoRoute>
<boxInbox>true</boxInbox>
<showLegend>false</showLegend>
<showLabels>false</showLabels>
<showRelAttributes>false</showRelAttributes>
<gridEnabled>false</gridEnabled>
<showGrid>false</showGrid>
<diagramColor>-1</diagramColor>
<display>false</display>
<notation>1</notation>
<objectViews>
<OView class="oracle.dbtools.crest.swingui.logical.TVEntity" oid="3D37FFFB-AE2A-C2E0-51A8-1FE523785272" otype="Entity" vid="57D2FDDE-F983-0345-03E2-8AEF523531EF">
<hideElementsInCurrentOnly>false</hideElementsInCurrentOnly>
<bounds x="859" y="60" width="287" height="221"/>
</OView>
<OView class="oracle.dbtools.crest.swingui.logical.TVEntity" oid="6051BE1E-5D21-C4C3-F59A-E64E248A3354" otype="Entity" vid="FF4C757A-2F9B-3431-9C07-BC4FF80100A1">
<hideElementsInCurrentOnly>false</hideElementsInCurrentOnly>
<bounds x="52" y="57" width="346" height="325"/>
</OView>
<OView class="oracle.dbtools.crest.swingui.logical.TVEntity" oid="C0E3E42E-1E1F-0E60-4B94-DE87DFE04A8A" otype="Entity" vid="D4DCF366-FF8F-E594-9F3F-0EE7BB9487DA">
<hideElementsInCurrentOnly>false</hideElementsInCurrentOnly>
<bounds x="51" y="441" width="284" height="224"/>
</OView>
<OView class="oracle.dbtools.crest.swingui.logical.TVEntity" oid="C2B8BD12-D1B0-D9D2-B954-2AC7DF4B51DD" otype="Entity" vid="45C7F880-A7E6-70A7-3A6A-A74AEB1A87DF">
<hideElementsInCurrentOnly>false</hideElementsInCurrentOnly>
<bounds x="52" y="717" width="317" height="251"/>
</OView>
<OView class="oracle.dbtools.crest.swingui.logical.TVEntity" oid="E21A04D0-8D6F-1B7F-C372-B1D9FDEEE53B" otype="Entity" vid="ABB098C2-C9B3-DD17-E192-DE2593511563">
<hideElementsInCurrentOnly>false</hideElementsInCurrentOnly>
<bounds x="481" y="55" width="232" height="221"/>
</OView>
</objectViews>
</Diagram>